{
  "color-space-for-untagged-svg-colors" : "display-p3",
  "fill" : {
    "automatic-gradient" : "extended-gray:1.00000,1.00000"
  },
  "groups" : [
    {
      "blur-material" : 0.5,
      "layers" : [
        {
          "fill-specializations" : [
            {
              "value" : {
                "solid" : "gray:0.16886,1.00000"
              }
            },
            {
              "appearance" : "dark",
              "value" : {
                "solid" : "gray:1.00000,1.00000"
              }
            }
          ],
          "hidden" : false,
          "image-name" : "bottom-front 2.svg",
          "name" : "bottom-front 2",
          "position" : {
            "scale" : 3.6,
            "translation-in-points" : [
              0,
              155.18906249999998
            ]
          }
        }
      ],
      "lighting" : "combined",
      "position" : {
        "scale" : 1,
        "translation-in-points" : [
          0,
          -14.7890625
        ]
      },
      "shadow" : {
        "kind" : "neutral",
        "opacity" : 0.5
      },
      "specular" : true,
      "translucency" : {
        "enabled" : true,
        "value" : 0.5
      }
    },
    {
      "blur-material" : null,
      "layers" : [
        {
          "fill-specializations" : [
            {
              "value" : {
                "solid" : "srgb:0.00000,0.62717,1.00000,1.00000"
              }
            },
            {
              "appearance" : "dark",
              "value" : {
                "solid" : "srgb:1.00000,0.57811,0.00000,1.00000"
              }
            }
          ],
          "hidden" : false,
          "image-name" : "bottom-card 2.svg",
          "name" : "bottom-card 2",
          "position" : {
            "scale" : 3.6,
            "translation-in-points" : [
              0,
              103.71875148901995
            ]
          }
        }
      ],
      "lighting" : "combined",
      "position" : {
        "scale" : 1,
        "translation-in-points" : [
          0,
          -14.7890625
        ]
      },
      "shadow" : {
        "kind" : "layer-color",
        "opacity" : 1
      },
      "translucency" : {
        "enabled" : true,
        "value" : 0.5
      }
    },
    {
      "blur-material" : 0.5,
      "hidden" : false,
      "layers" : [
        {
          "fill-specializations" : [
            {
              "value" : {
                "solid" : "gray:0.17000,1.00000"
              }
            },
            {
              "appearance" : "dark",
              "value" : {
                "solid" : "gray:0.83756,1.00000"
              }
            }
          ],
          "image-name" : "top-front 2.svg",
          "name" : "top-front 2",
          "position" : {
            "scale" : 3.6,
            "translation-in-points" : [
              0,
              59.7890625
            ]
          }
        }
      ],
      "lighting" : "combined",
      "position" : {
        "scale" : 1,
        "translation-in-points" : [
          0,
          -14.7890625
        ]
      },
      "shadow" : {
        "kind" : "neutral",
        "opacity" : 0.5
      },
      "specular" : true,
      "translucency" : {
        "enabled" : true,
        "value" : 0.5
      }
    },
    {
      "blur-material" : 0.5,
      "layers" : [
        {
          "blend-mode-specializations" : [
            {
              "appearance" : "dark",
              "value" : "normal"
            }
          ],
          "fill-specializations" : [
            {
              "value" : {
                "solid" : "srgb:0.00000,0.74659,0.47391,1.00000"
              }
            },
            {
              "appearance" : "dark",
              "value" : {
                "solid" : "srgb:0.00000,0.56905,0.57462,1.00000"
              }
            }
          ],
          "hidden" : false,
          "image-name" : "money-front.svg",
          "name" : "money-front",
          "position" : {
            "scale" : 3.6,
            "translation-in-points" : [
              3.6383991053900218,
              -86.63163464461024
            ]
          }
        },
        {
          "fill-specializations" : [
            {
              "value" : {
                "solid" : "srgb:0.00000,0.74659,0.47391,1.00000"
              }
            },
            {
              "appearance" : "dark",
              "value" : {
                "solid" : "srgb:0.00000,0.56905,0.57462,1.00000"
              }
            }
          ],
          "hidden" : false,
          "image-name" : "money-back.svg",
          "name" : "money-back",
          "position" : {
            "scale" : 3.6,
            "translation-in-points" : [
              0,
              -72.23162550300674
            ]
          }
        }
      ],
      "lighting" : "individual",
      "position" : {
        "scale" : 1,
        "translation-in-points" : [
          0,
          -14.7890625
        ]
      },
      "shadow" : {
        "kind" : "neutral",
        "opacity" : 0.5
      },
      "specular" : true,
      "translucency" : {
        "enabled" : true,
        "value" : 0.5
      }
    },
    {
      "layers" : [
        {
          "fill-specializations" : [
            {
              "value" : {
                "solid" : "gray:0.17000,1.00000"
              }
            },
            {
              "appearance" : "dark",
              "value" : {
                "solid" : "gray:0.64232,1.00000"
              }
            }
          ],
          "image-name" : "bg 2.svg",
          "name" : "bg 2",
          "position" : {
            "scale" : 3.6,
            "translation-in-points" : [
              0,
              14.7890625
            ]
          }
        }
      ],
      "position" : {
        "scale" : 1,
        "translation-in-points" : [
          0,
          -14.7890625
        ]
      },
      "shadow" : {
        "kind" : "neutral",
        "opacity" : 0.5
      },
      "translucency" : {
        "enabled" : true,
        "value" : 0.5
      }
    }
  ],
  "supported-platforms" : {
    "circles" : [
      "watchOS"
    ],
    "squares" : "shared"
  }
}